{
  "hash": "7572799b328eda2183033401b40a28df",
  "result": {
    "engine": "knitr",
    "markdown": "---\ntitle: \"data_check\"\nformat: html\n---\n\n# 生成AIに関連する求人数の推移(2023年)\n\n![画像](unnamed (1).png)\n![画像](unnamed (2).png)\n![画像](unnamed (3).png)\n\n[出典](https://www.hiringlab.org/jp/blog/2023/08/29/%E6%96%B0%E8%88%88%E5%8A%B4%E5%83%8D%E5%B8%82%E5%A0%B4%EF%BC%9A%E7%94%9F%E6%88%90ai%E3%81%AB%E9%96%A2%E9%80%A3%E3%81%99%E3%82%8B%E8%81%B7%E3%81%AE%E5%8F%B0%E9%A0%AD/)\n\n\n# 情報通信業雇用数の推移\n\n\n\n::: {.cell}\n\n:::\n\n\n\n::: {.cell}\n\n:::\n\n\n\n::: {.cell}\n\n:::\n\n\n\n\n::: {.cell}\n::: {.cell-output-display}\n`````{=html}\n<div data-pagedtable=\"false\">\n  <script data-pagedtable-source type=\"application/json\">\n{\"columns\":[{\"label\":[\"年\"],\"name\":[1],\"type\":[\"chr\"],\"align\":[\"left\"]},{\"label\":[\"月\"],\"name\":[2],\"type\":[\"chr\"],\"align\":[\"left\"]},{\"label\":[\"情報通信業雇用者数\"],\"name\":[3],\"type\":[\"dbl\"],\"align\":[\"right\"]},{\"label\":[\"月数\"],\"name\":[4],\"type\":[\"dbl\"],\"align\":[\"right\"]},{\"label\":[\"西暦\"],\"name\":[5],\"type\":[\"dbl\"],\"align\":[\"right\"]},{\"label\":[\"年月\"],\"name\":[6],\"type\":[\"date\"],\"align\":[\"right\"]}],\"data\":[{\"1\":\"平成14年\",\"2\":\"1月\",\"3\":\"153\",\"4\":\"1\",\"5\":\"2002\",\"6\":\"2002-01-01\"},{\"1\":\"平成14年\",\"2\":\"2月\",\"3\":\"156\",\"4\":\"2\",\"5\":\"2002\",\"6\":\"2002-02-01\"},{\"1\":\"平成14年\",\"2\":\"3月\",\"3\":\"156\",\"4\":\"3\",\"5\":\"2002\",\"6\":\"2002-03-01\"},{\"1\":\"平成14年\",\"2\":\"4月\",\"3\":\"159\",\"4\":\"4\",\"5\":\"2002\",\"6\":\"2002-04-01\"},{\"1\":\"平成14年\",\"2\":\"5月\",\"3\":\"157\",\"4\":\"5\",\"5\":\"2002\",\"6\":\"2002-05-01\"},{\"1\":\"平成14年\",\"2\":\"6月\",\"3\":\"159\",\"4\":\"6\",\"5\":\"2002\",\"6\":\"2002-06-01\"}],\"options\":{\"columns\":{\"min\":{},\"max\":[10]},\"rows\":{\"min\":[10],\"max\":[10]},\"pages\":{}}}\n  </script>\n</div>\n`````\n:::\n:::\n\n\n\n::: {.cell}\n::: {.cell-output .cell-output-stdout}\n\n```\ntibble [292 × 6] (S3: tbl_df/tbl/data.frame)\n $ 年                : chr [1:292] \"平成14年\" \"平成14年\" \"平成14年\" \"平成14年\" ...\n $ 月                : chr [1:292] \"1月\" \"2月\" \"3月\" \"4月\" ...\n $ 情報通信業雇用者数: num [1:292] 153 156 156 159 157 159 160 164 171 160 ...\n $ 月数              : num [1:292] 1 2 3 4 5 6 7 8 9 10 ...\n $ 西暦              : num [1:292] 2002 2002 2002 2002 2002 ...\n $ 年月              : Date[1:292], format: \"2002-01-01\" \"2002-02-01\" ...\n```\n\n\n:::\n:::\n\n\n\n\n::: {.cell}\n::: {.cell-output .cell-output-stdout}\n\n```\n                年                 月 情報通信業雇用者数               月数 \n                 0                  0                  0                  0 \n              西暦               年月 \n                 0                  0 \n```\n\n\n:::\n:::\n\n\n\n\n::: {.cell}\n::: {.cell-output .cell-output-stdout}\n\n```\n[1] \"年\"                 \"月\"                 \"情報通信業雇用者数\"\n[4] \"月数\"               \"西暦\"               \"年月\"              \n```\n\n\n:::\n:::\n\n\n\n::: {.cell}\n::: {.cell-output .cell-output-stdout}\n\n```\n   Min. 1st Qu.  Median    Mean 3rd Qu.    Max. \n  148.0   185.8   201.5   214.4   237.8   323.0 \n```\n\n\n:::\n:::\n\n\n\n\n::: {.cell}\n\n:::\n\n\n",
    "supporting": [
      "data_check_files"
    ],
    "filters": [
      "rmarkdown/pagebreak.lua"
    ],
    "includes": {
      "include-in-header": [
        "<link href=\"site_libs/pagedtable-1.1/css/pagedtable.css\" rel=\"stylesheet\" />\n<script src=\"site_libs/pagedtable-1.1/js/pagedtable.js\"></script>\n"
      ]
    },
    "engineDependencies": {},
    "preserve": {},
    "postProcess": true
  }
}